seersync/__init__.py
seersync/__main__.py
seersync/_version.py
seersync/app.py
seersync/models.py
seersync/rsync.py
seersync/ui.py
seersync-1.0.1.dist-info/LICENSE.txt
seersync-1.0.1.dist-info/METADATA
seersync-1.0.1.dist-info/WHEEL
seersync-1.0.1.dist-info/entry_points.txt
seersync-1.0.1.dist-info/top_level.txt
seersync-1.0.1.dist-info/RECORD
