Metadata-Version: 2.1
Name: seersync
Version: 1.0.1
Summary: Tool to list the changes that rsync would make if a given rsync command line gets executed
Home-page: https://github.com/lenkog/seersync
Author: Lenko Grigorov
Author-email: bnlsw@banica.org
License: BSD
Platform: UNKNOWN
Classifier: Programming Language :: Python :: 3
Classifier: License :: OSI Approved :: BSD License
Requires-Python: >=3.4
License-File: LICENSE.txt
Requires-Dist: argparse
